{
    "user_id": "aa",
    "style": "analytic_verbal",
    "current_day": 5,
    "progress": "started",
    "units": {
        "unit1": {
            "word": {
                "attempts": [
                    {
                        "day": 1,
                        "correct_rate": 1.0,
                        "wrong_questions": []
                    },
                    {
                        "day": 2,
                        "correct_rate": 1.0,
                        "wrong_questions": []
                    },
                    {
                        "day": 4,
                        "correct_rate": 1.0,
                        "wrong_questions": []
                    }
                ]
            },
            "sentence": {
                "attempts": [
                    {
                        "day": 3,
                        "correct_rate": 1.0,
                        "wrong_questions": []
                    },
                    {
                        "day": 4,
                        "correct_rate": 1.0,
                        "wrong_questions": []
                    }
                ]
            }
        },
        "unit2": {
            "word": {
                "attempts": []
            },
            "sentence": {
                "attempts": []
            }
        }
    },
    "video_watched": {
        "1": true,
        "3": true
    },
    "current_task_index": 0
}